LICENSE
MANIFEST.in
README.rst
classifiers.txt
setup.cfg
setup.py
collectd_haproxy/__init__.py
collectd_haproxy/compat.py
collectd_haproxy/connection.py
collectd_haproxy/metrics.py
collectd_haproxy/plugin.py
collectd_haproxy.egg-info/PKG-INFO
collectd_haproxy.egg-info/SOURCES.txt
collectd_haproxy.egg-info/dependency_links.txt
collectd_haproxy.egg-info/top_level.txt