Metadata-Version: 1.1
Name: collectd-haproxy
Version: 1.2.1
Summary: HAProxy stats plugin for collectd.
Home-page: http://github.com/wglass/collectd-haproxy
Author: William Glass
Author-email: william.glass@gmail.com
License: MIT
Platform: UNKNOWN
Classifier: Development Status :: 5 - Production/Stable
